opensearch_local/__init__.py
opensearch_local/our_opensearch.py
opensearch_local/our_vector_db.py
opensearch_local/utils.py
opensearch_local-0.0.8.dist-info/METADATA
opensearch_local-0.0.8.dist-info/WHEEL
opensearch_local-0.0.8.dist-info/top_level.txt
opensearch_local-0.0.8.dist-info/RECORD
