Metadata-Version: 2.4
Name: opensearch-local
Version: 0.0.8
Summary: PyPI Package for Circles opensearch-local Python
Home-page: https://github.com/circles-zone/opensearch-local-python-package
Author: Circles
Author-email: info@circlez.ai
Classifier: Programming Language :: Python :: 3
Classifier: License :: Other/Proprietary License
Classifier: Operating System :: OS Independent
Requires-Dist: python-sdk-remote
Requires-Dist: event-local>=0.0.9
Requires-Dist: contact-local>=0.0.71
Requires-Dist: opensearch-py
Dynamic: author
Dynamic: author-email
Dynamic: classifier
Dynamic: description
Dynamic: description-content-type
Dynamic: home-page
Dynamic: requires-dist
Dynamic: summary
